.hgignore
CHANGES.txt
LICENSE.txt
README.txt
bootstrap.py
buildout.cfg
setup.py
js/__init__.py
js.jquery_url_parser.egg-info/PKG-INFO
js.jquery_url_parser.egg-info/SOURCES.txt
js.jquery_url_parser.egg-info/dependency_links.txt
js.jquery_url_parser.egg-info/entry_points.txt
js.jquery_url_parser.egg-info/namespace_packages.txt
js.jquery_url_parser.egg-info/not-zip-safe
js.jquery_url_parser.egg-info/requires.txt
js.jquery_url_parser.egg-info/top_level.txt
js/jquery_url_parser/__init__.py
js/jquery_url_parser/test_jquery-url-parser.txt
js/jquery_url_parser/resources/README.txt
js/jquery_url_parser/resources/jquery.url.js