Metadata-Version: 1.0
Name: js.jquery-url-parser
Version: 2.0
Summary: Fanstatic packaging of jQuery-URL-Parser
Home-page: UNKNOWN
Author: Fanstatic Developers
Author-email: fanstatic@googlegroups.com
License: BSD
Platform: UNKNOWN
